[
    {
        "title": "Alonso denies claim that Aston Martin's Hungarian GP upgrade will decide his F1 future",
        "link": "https://www.autosport.com/f1/news/fernando-alonso-denies-claim-that-aston-martins-f1-hungarian-gp-upgrade-will-decide-his-future/10835579/?utm_source=RSS&utm_medium=referral&utm_campaign=RSS-F1&utm_term=News&utm_content=uk",
        "image_url": "https://cdn-9.motorsport.com/images/amp/27NQzBX0/s6/fernando-alonso-aston-martin-r-2.jpg",
        "w": 1200,
        "h": 799,
        "focus_y": 0.5,
        "source_title1": "AUTOSPORT",
        "source_title2": "F1",
        "source_color": "#000000",
        "flag": "🇬🇧"
    },
    {
        "title": "Alonso: Silverstone will be \"not fun to drive\" with 2026 F1 cars",
        "link": "https://www.autosport.com/f1/news/fernando-alonso-silverstone-will-be-very-different-and-not-fun-to-drive-in-2026-f1-cars/10835549/?utm_source=RSS&utm_medium=referral&utm_campaign=RSS-F1&utm_term=News&utm_content=uk",
        "image_url": "https://cdn-8.motorsport.com/images/amp/6Vy7v17Y/s6/fernando-alonso-aston-martin-r-2.jpg",
        "w": 1200,
        "h": 799,
        "focus_y": 0.5,
        "source_title1": "AUTOSPORT",
        "source_title2": "F1",
        "source_color": "#000000",
        "flag": "🇬🇧"
    },
    {
        "title": "Motorsport UK and BRDC unite to develop young British drivers",
        "link": "https://www.autosport.com/national/news/motorsport-uk-and-brdc-unite-to-develop-young-british-drivers/10835534/?utm_source=RSS&utm_medium=referral&utm_campaign=RSS-F1&utm_term=News&utm_content=uk",
        "image_url": "https://cdn-1.motorsport.com/images/amp/24QerAXY/s6/a-general-view-of-the-brdc-bui.jpg",
        "w": 1200,
        "h": 799,
        "focus_y": 0.5,
        "source_title1": "AUTOSPORT",
        "source_title2": "F1",
        "source_color": "#000000",
        "flag": "🇬🇧"
    },
    {
        "title": "F1 drivers to take to Lego minicars at British GP",
        "link": "https://www.autosport.com/f1/news/f1-drivers-to-take-to-lego-minicars-at-british-gp/10835478/?utm_source=RSS&utm_medium=referral&utm_campaign=RSS-F1&utm_term=News&utm_content=uk",
        "image_url": "https://cdn-5.motorsport.com/images/amp/6lmdbqN0/s6/lego-minicars.jpg",
        "w": 1200,
        "h": 799,
        "focus_y": 0.5,
        "source_title1": "AUTOSPORT",
        "source_title2": "F1",
        "source_color": "#000000",
        "flag": "🇬🇧"
    },
    {
        "title": "Vote: Autosport Best of the Month for June 2026",
        "link": "https://www.autosport.com/general/news/vote-autosport-best-of-the-month-for-june-2026/10835386/?utm_source=RSS&utm_medium=referral&utm_campaign=RSS-F1&utm_term=News&utm_content=uk",
        "image_url": "https://cdn-8.motorsport.com/images/amp/2GdwM7KY/s6/image.jpg",
        "w": 1200,
        "h": 799,
        "focus_y": 0.5,
        "source_title1": "AUTOSPORT",
        "source_title2": "F1",
        "source_color": "#000000",
        "flag": "🇬🇧"
    },
    {
        "title": "McLaren still to investigate why it's losing to Mercedes on the straights, despite same PU",
        "link": "https://www.autosport.com/f1/news/mclaren-still-to-investigate-why-its-losing-to-mercedes-on-the-straights-despite-same-pu/10835343/?utm_source=RSS&utm_medium=referral&utm_campaign=RSS-F1&utm_term=News&utm_content=uk",
        "image_url": "https://cdn-2.motorsport.com/images/amp/0JXwndEY/s6/lando-norris-mclaren-george-ru.jpg",
        "w": 1200,
        "h": 799,
        "focus_y": 0.5,
        "source_title1": "AUTOSPORT",
        "source_title2": "F1",
        "source_color": "#000000",
        "flag": "🇬🇧"
    },
    {
        "title": "Autosport Retro video: Remembering the 1987 British GP",
        "link": "https://www.autosport.com/f1/news/autosport-retro-video-remembering-the-1987-british-gp/10835271/?utm_source=RSS&utm_medium=referral&utm_campaign=RSS-F1&utm_term=News&utm_content=uk",
        "image_url": "https://cdn-6.motorsport.com/images/amp/24vpv7g6/s6/podium-race-winner-nigel-manse.jpg",
        "w": 1200,
        "h": 799,
        "focus_y": 0.5,
        "source_title1": "AUTOSPORT",
        "source_title2": "F1",
        "source_color": "#000000",
        "flag": "🇬🇧"
    },
    {
        "title": "Williams plans “almost entirely new car” by Azerbaijan GP",
        "link": "https://www.autosport.com/f1/news/williams-plans-almost-entirely-new-car-by-azerbaijan-gp/10835267/?utm_source=RSS&utm_medium=referral&utm_campaign=RSS-F1&utm_term=News&utm_content=uk",
        "image_url": "https://cdn-6.motorsport.com/images/amp/25d384n0/s6/alexander-albon-williams-2.jpg",
        "w": 1200,
        "h": 799,
        "focus_y": 0.5,
        "source_title1": "AUTOSPORT",
        "source_title2": "F1",
        "source_color": "#000000",
        "flag": "🇬🇧"
    },
    {
        "title": "Is Verstappen to McLaren a genuine possibility?",
        "link": "https://www.autosport.com/f1/news/verstappen-to-mclaren-f1-talks/10835116/?utm_source=RSS&utm_medium=referral&utm_campaign=RSS-F1&utm_term=News&utm_content=uk",
        "image_url": "https://cdn-5.motorsport.com/images/amp/0arKPwM2/s6/max-verstappen-red-bull-racing-2.jpg",
        "w": 1200,
        "h": 799,
        "focus_y": 0.5,
        "source_title1": "AUTOSPORT",
        "source_title2": "F1",
        "source_color": "#000000",
        "flag": "🇬🇧"
    },
    {
        "title": "Newey hoping to keep Alonso at Aston Martin for F1 2027",
        "link": "https://www.autosport.com/f1/news/newey-alonso-aston-martin-f1-2027/10835021/?utm_source=RSS&utm_medium=referral&utm_campaign=RSS-F1&utm_term=News&utm_content=uk",
        "image_url": "https://cdn-5.motorsport.com/images/amp/6Vy7v17Y/s6/fernando-alonso-aston-martin-r-2.jpg",
        "w": 1200,
        "h": 799,
        "focus_y": 0.5,
        "source_title1": "AUTOSPORT",
        "source_title2": "F1",
        "source_color": "#000000",
        "flag": "🇬🇧"
    },
    {
        "title": "Verstappen dismisses talk of title challenge in F1 2026",
        "link": "https://www.autosport.com/f1/news/verstappen-dismisses-f1-title-challenge/10835012/?utm_source=RSS&utm_medium=referral&utm_campaign=RSS-F1&utm_term=News&utm_content=uk",
        "image_url": "https://cdn-1.motorsport.com/images/amp/YBVoO4MY/s6/andrea-kimi-antonelli-mercedes-2.jpg",
        "w": 1200,
        "h": 800,
        "focus_y": 0.5,
        "source_title1": "AUTOSPORT",
        "source_title2": "F1",
        "source_color": "#000000",
        "flag": "🇬🇧"
    },
    {
        "title": "Why Verstappen burst out laughing during British GP simulator runs",
        "link": "https://www.autosport.com/f1/news/why-max-verstappen-burst-out-laughing-during-silverstone-f1-simulator-runs/10834845/?utm_source=RSS&utm_medium=referral&utm_campaign=RSS-F1&utm_term=News&utm_content=uk",
        "image_url": "https://cdn-7.motorsport.com/images/amp/Y9lL8rb2/s6/max-verstappen-red-bull-racing.jpg",
        "w": 1200,
        "h": 799,
        "focus_y": 0.5,
        "source_title1": "AUTOSPORT",
        "source_title2": "F1",
        "source_color": "#000000",
        "flag": "🇬🇧"
    },
    {
        "title": "How Russell resorted to \"abnormal\" driving style to win F1 Austrian GP",
        "link": "https://www.autosport.com/f1/news/how-russell-resorted-to-abnormal-driving-style-to-win-f1-austrian-gp/10834814/?utm_source=RSS&utm_medium=referral&utm_campaign=RSS-F1&utm_term=News&utm_content=uk",
        "image_url": "https://cdn-4.motorsport.com/images/amp/2Gdwb9KY/s6/george-russell-mercedes-2.jpg",
        "w": 1200,
        "h": 799,
        "focus_y": 0.5,
        "source_title1": "AUTOSPORT",
        "source_title2": "F1",
        "source_color": "#000000",
        "flag": "🇬🇧"
    },
    {
        "title": "Mercedes boss questions Ferrari's \"limitless\" F1 upgrades amid budget cap era",
        "link": "https://www.autosport.com/f1/news/mercedes-boss-questions-how-ferrari-can-afford-limitless-f1-upgrades/10834765/?utm_source=RSS&utm_medium=referral&utm_campaign=RSS-F1&utm_term=News&utm_content=uk",
        "image_url": "https://cdn-1.motorsport.com/images/amp/2eZgDGlY/s6/lewis-hamilton-ferrari-3.jpg",
        "w": 1200,
        "h": 799,
        "focus_y": 0.5,
        "source_title1": "AUTOSPORT",
        "source_title2": "F1",
        "source_color": "#000000",
        "flag": "🇬🇧"
    },
    {
        "title": "Wolff: Verstappen factor behind Red Bull's Austrian GP fight against Mercedes",
        "link": "https://www.autosport.com/f1/news/toto-wolff-points-to-max-verstappen-factor-behind-red-bulls-austria-pace/10834670/?utm_source=RSS&utm_medium=referral&utm_campaign=RSS-F1&utm_term=News&utm_content=uk",
        "image_url": "https://cdn-2.motorsport.com/images/amp/2eZgRN1Y/s6/george-russell-mercedes-kimi-a-2.jpg",
        "w": 1200,
        "h": 799,
        "focus_y": 0.5,
        "source_title1": "AUTOSPORT",
        "source_title2": "F1",
        "source_color": "#000000",
        "flag": "🇬🇧"
    },
    {
        "title": "Hamilton and Leclerc confused by woeful Ferrari pace in Austrian GP",
        "link": "https://www.autosport.com/f1/news/lewis-hamilton-charles-leclerc-confused-by-woeful-ferrari-race-pace-in-austria/10834669/?utm_source=RSS&utm_medium=referral&utm_campaign=RSS-F1&utm_term=News&utm_content=uk",
        "image_url": "https://cdn-8.motorsport.com/images/amp/0ZqALvN6/s6/charles-leclerc-ferrari-lewis-.jpg",
        "w": 1200,
        "h": 800,
        "focus_y": 0.5,
        "source_title1": "AUTOSPORT",
        "source_title2": "F1",
        "source_color": "#000000",
        "flag": "🇬🇧"
    },
    {
        "title": "Piastri escapes punishment at F1 Austrian GP",
        "link": "https://www.autosport.com/f1/news/oscar-piastri-summoned-to-f1-austrian-gp-stewards/10834540/?utm_source=RSS&utm_medium=referral&utm_campaign=RSS-F1&utm_term=News&utm_content=uk",
        "image_url": "https://cdn-8.motorsport.com/images/amp/0arKZBr2/s6/oscar-piastri-mclaren.jpg",
        "w": 1200,
        "h": 800,
        "focus_y": 0.5,
        "source_title1": "AUTOSPORT",
        "source_title2": "F1",
        "source_color": "#000000",
        "flag": "🇬🇧"
    },
    {
        "title": "F1 Austrian GP: Russell holds off Verstappen to win and cut Antonelli’s championship lead",
        "link": "https://www.autosport.com/f1/news/f1-austrian-gp-race-report-/10834502/?utm_source=RSS&utm_medium=referral&utm_campaign=RSS-F1&utm_term=News&utm_content=uk",
        "image_url": "https://cdn-7.motorsport.com/images/amp/0o5P3LbY/s6/george-russell-mercedes-3.jpg",
        "w": 1200,
        "h": 799,
        "focus_y": 0.5,
        "source_title1": "AUTOSPORT",
        "source_title2": "F1",
        "source_color": "#000000",
        "flag": "🇬🇧"
    },
    {
        "title": "“They know” – Verstappen says Red Bull is aware of what’s needed to keep him for F1 2027",
        "link": "https://www.autosport.com/f1/news/they-know-max-verstappen-says-red-bull-knows-whats-needed-to-keep-him-for-2027/10834364/?utm_source=RSS&utm_medium=referral&utm_campaign=RSS-F1&utm_term=News&utm_content=uk",
        "image_url": "https://cdn-9.motorsport.com/images/amp/2y7AqEn6/s6/max-verstappen-red-bull-racing-2.jpg",
        "w": 1200,
        "h": 799,
        "focus_y": 0.5,
        "source_title1": "AUTOSPORT",
        "source_title2": "F1",
        "source_color": "#000000",
        "flag": "🇬🇧"
    },
    {
        "title": "Cadillac's F1 updates show improved pace, but hot Austrian GP will test its capabilities",
        "link": "https://www.autosport.com/f1/news/cadillacs-f1-updates-show-improved-pace-but-hot-austrian-gp-will-be-the-litmus-test/10834318/?utm_source=RSS&utm_medium=referral&utm_campaign=RSS-F1&utm_term=News&utm_content=uk",
        "image_url": "https://cdn-6.motorsport.com/images/amp/2Qe8qPX2/s6/valtteri-bottas-cadillac-racin-2.jpg",
        "w": 1200,
        "h": 799,
        "focus_y": 0.5,
        "source_title1": "AUTOSPORT",
        "source_title2": "F1",
        "source_color": "#000000",
        "flag": "🇬🇧"
    },
    {
        "title": "Red Bull apologises to Max Verstappen after technical issue caused F1 qualifying crash",
        "link": "https://www.autosport.com/f1/news/red-bull-takes-blame-for-verstappens-austrian-gp-qualifying-crash/10834243/?utm_source=RSS&utm_medium=referral&utm_campaign=RSS-F1&utm_term=News&utm_content=uk",
        "image_url": "https://cdn-9.motorsport.com/images/amp/0o5Pb3lY/s6/max-verstappen-red-bull-racing.jpg",
        "w": 1200,
        "h": 798,
        "focus_y": 0.5,
        "source_title1": "AUTOSPORT",
        "source_title2": "F1",
        "source_color": "#000000",
        "flag": "🇬🇧"
    },
    {
        "title": "Why Antonelli aborted his fastest lap in Austrian GP qualifying",
        "link": "https://www.autosport.com/f1/news/why-kimi-antonelli-aborted-his-fastest-lap-in-austrian-gp-qualifying/10834163/?utm_source=RSS&utm_medium=referral&utm_campaign=RSS-F1&utm_term=News&utm_content=uk",
        "image_url": "https://cdn-6.motorsport.com/images/amp/0rVx3950/s6/andrea-kimi-antonelli-mercedes-2.jpg",
        "w": 1200,
        "h": 799,
        "focus_y": 0.5,
        "source_title1": "AUTOSPORT",
        "source_title2": "F1",
        "source_color": "#000000",
        "flag": "🇬🇧"
    },
    {
        "title": "Verstappen questions \"crazy\" delay in double yellow flags as the FIA responds",
        "link": "https://www.autosport.com/f1/news/thats-crazy-max-verstappen-questions-delay-in-double-yellow-flags-fia-explains/10834149/?utm_source=RSS&utm_medium=referral&utm_campaign=RSS-F1&utm_term=News&utm_content=uk",
        "image_url": "https://cdn-8.motorsport.com/images/amp/6Al7j1DY/s6/max-verstappen-red-bull-racing.jpg",
        "w": 1200,
        "h": 799,
        "focus_y": 0.5,
        "source_title1": "AUTOSPORT",
        "source_title2": "F1",
        "source_color": "#000000",
        "flag": "🇬🇧"
    },
    {
        "title": "Russell explains meaning behind Wolff's \"just drive\" radio message in Austrian GP qualifying",
        "link": "https://www.autosport.com/f1/news/george-russell-explains-toto-wolffs-just-drive-radio-message/10834135/?utm_source=RSS&utm_medium=referral&utm_campaign=RSS-F1&utm_term=News&utm_content=uk",
        "image_url": "https://cdn-1.motorsport.com/images/amp/0R7wneE2/s6/george-russell-mercedes-toto-w.jpg",
        "w": 1200,
        "h": 799,
        "focus_y": 0.5,
        "source_title1": "AUTOSPORT",
        "source_title2": "F1",
        "source_color": "#000000",
        "flag": "🇬🇧"
    },
    {
        "title": "Verstappen on \"odd\" Austrian GP qualifying crash: \"As I turned the wheel I was gone\"",
        "link": "https://www.autosport.com/f1/news/max-verstappen-on-odd-austria-f1-qualifying-crash-as-i-turned-the-wheel-i-was-gone/10834082/?utm_source=RSS&utm_medium=referral&utm_campaign=RSS-F1&utm_term=News&utm_content=uk",
        "image_url": "https://cdn-2.motorsport.com/images/amp/0JXwggOY/s6/max-verstappen-red-bull-racing.jpg",
        "w": 1200,
        "h": 799,
        "focus_y": 0.5,
        "source_title1": "AUTOSPORT",
        "source_title2": "F1",
        "source_color": "#000000",
        "flag": "🇬🇧"
    },
    {
        "title": "Why Russell escaped investigation for yellow flag on Austrian GP pole lap",
        "link": "https://www.autosport.com/f1/news/why-russell-escaped-investigation-for-yellow-flag-on-austrian-gp-pole-lap/10834061/?utm_source=RSS&utm_medium=referral&utm_campaign=RSS-F1&utm_term=News&utm_content=uk",
        "image_url": "https://cdn-3.motorsport.com/images/amp/YpbPpZ30/s6/george-russell-mercedes-3.jpg",
        "w": 1200,
        "h": 799,
        "focus_y": 0.5,
        "source_title1": "AUTOSPORT",
        "source_title2": "F1",
        "source_color": "#000000",
        "flag": "🇬🇧"
    },
    {
        "title": "F1 Austrian GP: Russell avoids investigation to take pole after Verstappen crash",
        "link": "https://www.autosport.com/f1/news/f1-austrian-gp-qualifying-report-10834036/10834036/?utm_source=RSS&utm_medium=referral&utm_campaign=RSS-F1&utm_term=News&utm_content=uk",
        "image_url": "https://cdn-2.motorsport.com/images/amp/2Qe8qav2/s6/george-russell-mercedes-2.jpg",
        "w": 1200,
        "h": 799,
        "focus_y": 0.5,
        "source_title1": "AUTOSPORT",
        "source_title2": "F1",
        "source_color": "#000000",
        "flag": "🇬🇧"
    },
    {
        "title": "Former F1 chief Ecclestone backs push for V8 engines",
        "link": "https://www.autosport.com/f1/news/former-f1-chief-bernie-ecclestone-backs-push-for-v8-engines/10834010/?utm_source=RSS&utm_medium=referral&utm_campaign=RSS-F1&utm_term=News&utm_content=uk",
        "image_url": "https://cdn-8.motorsport.com/images/amp/2GdwgrlY/s6/bernie-ecclestone-2.jpg",
        "w": 1200,
        "h": 799,
        "focus_y": 0.5,
        "source_title1": "AUTOSPORT",
        "source_title2": "F1",
        "source_color": "#000000",
        "flag": "🇬🇧"
    },
    {
        "title": "Monaghan set to join Cadillac, but hasn’t resigned from Red Bull yet",
        "link": "https://www.autosport.com/f1/news/paul-monaghan-set-to-join-cadillac-but-hasnt-resigned-from-red-bull-yet/10833956/?utm_source=RSS&utm_medium=referral&utm_campaign=RSS-F1&utm_term=News&utm_content=uk",
        "image_url": "https://cdn-6.motorsport.com/images/amp/YBVomPzY/s6/paul-monaghan-head-of-car-engi.jpg",
        "w": 1200,
        "h": 799,
        "focus_y": 0.5,
        "source_title1": "AUTOSPORT",
        "source_title2": "F1",
        "source_color": "#000000",
        "flag": "🇬🇧"
    },
    {
        "title": "F1 Austrian GP: Russell beats Antonelli to top spot in final practice",
        "link": "https://www.autosport.com/f1/news/f1-austrian-gp-fp3-report/10833919/?utm_source=RSS&utm_medium=referral&utm_campaign=RSS-F1&utm_term=News&utm_content=uk",
        "image_url": "https://cdn-6.motorsport.com/images/amp/Y9lL8n72/s6/george-russell-mercedes-2.jpg",
        "w": 1200,
        "h": 799,
        "focus_y": 0.5,
        "source_title1": "AUTOSPORT",
        "source_title2": "F1",
        "source_color": "#000000",
        "flag": "🇬🇧"
    },
    {
        "title": "Road vs race track: Why the 2031 engine debate remains a complicated puzzle",
        "link": "https://www.autosport.com/f1/news/naturally-aspirated-v8-vs-turbo-why-the-2031-engine-debate-remains-a-complicated-puzzle/10833849/?utm_source=RSS&utm_medium=referral&utm_campaign=RSS-F1&utm_term=News&utm_content=uk",
        "image_url": "https://cdn-6.motorsport.com/images/amp/68ynkOX0/s6/motore-ford-cosworth-v8-gp-di-.jpg",
        "w": 1200,
        "h": 799,
        "focus_y": 0.5,
        "source_title1": "AUTOSPORT",
        "source_title2": "F1",
        "source_color": "#000000",
        "flag": "🇬🇧"
    },
    {
        "title": "What's behind Red Bull's \"hit-and-miss\" issues during first test of crucial F1 upgrade?",
        "link": "https://www.autosport.com/f1/news/why-red-bull-suffered-hit-and-miss-issues-during-first-test-of-crucial-f1-upgrade/10833740/?utm_source=RSS&utm_medium=referral&utm_campaign=RSS-F1&utm_term=News&utm_content=uk",
        "image_url": "https://cdn-9.motorsport.com/images/amp/YP7rGXo2/s6/isack-hadjar-red-bull-racing-2.jpg",
        "w": 1200,
        "h": 799,
        "focus_y": 0.5,
        "source_title1": "AUTOSPORT",
        "source_title2": "F1",
        "source_color": "#000000",
        "flag": "🇬🇧"
    },
    {
        "title": "Why McLaren hasn't run its \"McMacarena\" wing in Austria",
        "link": "https://www.autosport.com/f1/news/why-mclaren-hasnt-run-its-mcmacarena-wing-in-austria/10833641/?utm_source=RSS&utm_medium=referral&utm_campaign=RSS-F1&utm_term=News&utm_content=uk",
        "image_url": "https://cdn-8.motorsport.com/images/amp/2y7AqVe6/s6/mclaren-technical-detail.jpg",
        "w": 1200,
        "h": 798,
        "focus_y": 0.5,
        "source_title1": "AUTOSPORT",
        "source_title2": "F1",
        "source_color": "#000000",
        "flag": "🇬🇧"
    },
    {
        "title": "Spotlight back on Verstappen's Red Bull future after Monaghan exit rumours",
        "link": "https://www.autosport.com/f1/news/red-bull-confident-of-keeping-max-verstappen-despite-paul-monaghan-exit-rumours/10833638/?utm_source=RSS&utm_medium=referral&utm_campaign=RSS-F1&utm_term=News&utm_content=uk",
        "image_url": "https://cdn-5.motorsport.com/images/amp/YXRAJ350/s6/lando-norris-mclaren-f1-team-2.jpg",
        "w": 960,
        "h": 640,
        "focus_y": 0.5,
        "source_title1": "AUTOSPORT",
        "source_title2": "F1",
        "source_color": "#000000",
        "flag": "🇬🇧"
    },
    {
        "title": "F1 Austrian GP: Antonelli completes perfect Friday by topping FP2",
        "link": "https://www.autosport.com/f1/news/f1-austrian-gp-fp2-report-10833605/10833605/?utm_source=RSS&utm_medium=referral&utm_campaign=RSS-F1&utm_term=News&utm_content=uk",
        "image_url": "https://cdn-3.motorsport.com/images/amp/YE9w1DpY/s6/andrea-kimi-antonelli-mercedes.jpg",
        "w": 1200,
        "h": 799,
        "focus_y": 0.5,
        "source_title1": "AUTOSPORT",
        "source_title2": "F1",
        "source_color": "#000000",
        "flag": "🇬🇧"
    },
    {
        "title": "FIA bans Ferrari style exhaust wings in F1 2027",
        "link": "https://www.autosport.com/f1/news/fia-bans-ferrari-style-exhaust-wings-in-f1-2027/10833621/?utm_source=RSS&utm_medium=referral&utm_campaign=RSS-F1&utm_term=News&utm_content=uk",
        "image_url": "https://cdn-2.motorsport.com/images/amp/YMX3mRL2/s6/ferrari-rear-technical-detail.jpg",
        "w": 1200,
        "h": 799,
        "focus_y": 0.5,
        "source_title1": "AUTOSPORT",
        "source_title2": "F1",
        "source_color": "#000000",
        "flag": "🇬🇧"
    },
    {
        "title": "F1 Austrian GP: Antonelli pips Russell to top FP1, Norris hit with hydraulics issue",
        "link": "https://www.autosport.com/f1/news/f1-austrian-gp-fp1-report/10833511/?utm_source=RSS&utm_medium=referral&utm_campaign=RSS-F1&utm_term=News&utm_content=uk",
        "image_url": "https://cdn-5.motorsport.com/images/amp/0Ld57BJ0/s6/andrea-kimi-antonelli-mercedes.jpg",
        "w": 1200,
        "h": 799,
        "focus_y": 0.5,
        "source_title1": "AUTOSPORT",
        "source_title2": "F1",
        "source_color": "#000000",
        "flag": "🇬🇧"
    },
    {
        "title": "Top 10 McLaren F1 drivers ranked: Senna, Prost, Hamilton and more",
        "link": "https://www.autosport.com/f1/news/top-10-mclaren-f1-drivers-ranked-senna-prost-hamilton-and-more/7227506/?utm_source=RSS&utm_medium=referral&utm_campaign=RSS-F1&utm_term=News&utm_content=uk",
        "image_url": "https://cdn-5.motorsport.com/images/amp/2wBzd5e0/s6/formula-1-belgian-gp-1988-alai-2.jpg",
        "w": 1200,
        "h": 800,
        "focus_y": 0.5,
        "source_title1": "AUTOSPORT",
        "source_title2": "F1",
        "source_color": "#000000",
        "flag": "🇬🇧"
    },
    {
        "title": "Red Bull details Austrian GP updates; Audi, Cadillac bring improvements",
        "link": "https://www.autosport.com/f1/news/red-bull-details-austrian-gp-updates-audi-cadillac-bring-improvements/10833481/?utm_source=RSS&utm_medium=referral&utm_campaign=RSS-F1&utm_term=News&utm_content=uk",
        "image_url": "https://cdn-7.motorsport.com/images/amp/2jED5mM0/s6/redbull-technical-detail-2.jpg",
        "w": 1200,
        "h": 800,
        "focus_y": 0.5,
        "source_title1": "AUTOSPORT",
        "source_title2": "F1",
        "source_color": "#000000",
        "flag": "🇬🇧"
    },
    {
        "title": "Verstappen targets Spa 24 Hours as he asks organisers to avoid F1 clash",
        "link": "https://www.autosport.com/f1/news/max-verstappen-eyes-spa-24-hours-outing-as-he-asks-organisers-to-avoid-f1-clash/10833453/?utm_source=RSS&utm_medium=referral&utm_campaign=RSS-F1&utm_term=News&utm_content=uk",
        "image_url": "https://cdn-3.motorsport.com/images/amp/Y9lL8rb2/s6/max-verstappen-red-bull-racing.jpg",
        "w": 1200,
        "h": 799,
        "focus_y": 0.5,
        "source_title1": "AUTOSPORT",
        "source_title2": "F1",
        "source_color": "#000000",
        "flag": "🇬🇧"
    },
    {
        "title": "The best FIA relations in years: How F1 drivers won the penalty points fight",
        "link": "https://www.autosport.com/f1/news/how-the-best-fia-relations-since-charlie-whiting-helped-drivers-win-the-penalty-points-fight-/10833407/?utm_source=RSS&utm_medium=referral&utm_campaign=RSS-F1&utm_term=News&utm_content=uk",
        "image_url": "https://cdn-8.motorsport.com/images/amp/0mXRw1q6/s6/esteban-ocon-haas-f1-team-fran.jpg",
        "w": 1200,
        "h": 799,
        "focus_y": 0.5,
        "source_title1": "AUTOSPORT",
        "source_title2": "F1",
        "source_color": "#000000",
        "flag": "🇬🇧"
    },
    {
        "title": "How worried should Ferrari’s F1 rivals be about its progress and engine upgrade?",
        "link": "https://www.autosport.com/f1/news/how-worried-f1-rivals-really-are-about-ferraris-progress-and-engine-upgrade/10833373/?utm_source=RSS&utm_medium=referral&utm_campaign=RSS-F1&utm_term=News&utm_content=uk",
        "image_url": "https://cdn-3.motorsport.com/images/amp/YBVoDnJY/s6/andrea-kimi-antonelli-mercedes-2.jpg",
        "w": 1200,
        "h": 800,
        "focus_y": 0.5,
        "source_title1": "AUTOSPORT",
        "source_title2": "F1",
        "source_color": "#000000",
        "flag": "🇬🇧"
    },
    {
        "title": "Mercedes forced into diffuser tweaks after rival complaints and FIA intervention",
        "link": "https://www.autosport.com/f1/news/mercedes-forced-to-tweak-f1-diffuser-after-rival-complaints/10833319/?utm_source=RSS&utm_medium=referral&utm_campaign=RSS-F1&utm_term=News&utm_content=uk",
        "image_url": "https://cdn-7.motorsport.com/images/amp/6n7AE3e0/s6/diffusore-mercedes-2.jpg",
        "w": 1200,
        "h": 799,
        "focus_y": 0.5,
        "source_title1": "AUTOSPORT",
        "source_title2": "F1",
        "source_color": "#000000",
        "flag": "🇬🇧"
    },
    {
        "title": "How crucial is Red Bull's Austrian GP upgrade for Verstappen's F1 future?",
        "link": "https://www.autosport.com/f1/news/how-crucial-is-red-bulls-austrian-gp-upgrade-for-verstappens-f1-future/10833277/?utm_source=RSS&utm_medium=referral&utm_campaign=RSS-F1&utm_term=News&utm_content=uk",
        "image_url": "https://cdn-4.motorsport.com/images/amp/2dE7ZywY/s6/max-verstappen-red-bull-racing-2.jpg",
        "w": 1200,
        "h": 799,
        "focus_y": 0.5,
        "source_title1": "AUTOSPORT",
        "source_title2": "F1",
        "source_color": "#000000",
        "flag": "🇬🇧"
    },
    {
        "title": "Hamilton details neck injury that affected start of 2025 F1 season",
        "link": "https://www.autosport.com/f1/news/lewis-hamilton-explains-neck-injury-that-affected-2025-f1-season/10833256/?utm_source=RSS&utm_medium=referral&utm_campaign=RSS-F1&utm_term=News&utm_content=uk",
        "image_url": "https://cdn-2.motorsport.com/images/amp/2eZgDpjY/s6/lewis-hamilton-ferrari-2.jpg",
        "w": 1200,
        "h": 799,
        "focus_y": 0.5,
        "source_title1": "AUTOSPORT",
        "source_title2": "F1",
        "source_color": "#000000",
        "flag": "🇬🇧"
    },
    {
        "title": "FIA abolishes presidential term limits",
        "link": "https://www.autosport.com/f1/news/fia-abolishes-presidential-term-limits-at-macau-meetings/10833214/?utm_source=RSS&utm_medium=referral&utm_campaign=RSS-F1&utm_term=News&utm_content=uk",
        "image_url": "https://cdn-7.motorsport.com/images/amp/24vxNN56/s6/mohammed-ben-sulayem-fia-presi-2.jpg",
        "w": 1200,
        "h": 799,
        "focus_y": 0.5,
        "source_title1": "AUTOSPORT",
        "source_title2": "F1",
        "source_color": "#000000",
        "flag": "🇬🇧"
    },
    {
        "title": "Mercedes delivers F1 engine fixes in Austria after Antonelli’s Barcelona GP retirement",
        "link": "https://www.autosport.com/f1/news/mercedes-to-introduce-f1-engine-fixes-in-austria-after-kimi-antonellis-barcelona-gp-retirement/10833135/?utm_source=RSS&utm_medium=referral&utm_campaign=RSS-F1&utm_term=News&utm_content=uk",
        "image_url": "https://cdn-6.motorsport.com/images/amp/6x7ZXo7Y/s6/andrea-kimi-antonelli-mercedes-2.jpg",
        "w": 1200,
        "h": 799,
        "focus_y": 0.5,
        "source_title1": "AUTOSPORT",
        "source_title2": "F1",
        "source_color": "#000000",
        "flag": "🇬🇧"
    },
    {
        "title": "Why Honda will just use one of its two upgrade opportunities in F1 2026",
        "link": "https://www.autosport.com/f1/news/why-honda-will-just-use-one-of-its-two-upgrade-opportunities-in-f1-2026/10833102/?utm_source=RSS&utm_medium=referral&utm_campaign=RSS-F1&utm_term=News&utm_content=uk",
        "image_url": "https://cdn-8.motorsport.com/images/amp/6zoJdZJ0/s6/fernando-alonso-aston-martin-r-2.jpg",
        "w": 1200,
        "h": 799,
        "focus_y": 0.5,
        "source_title1": "AUTOSPORT",
        "source_title2": "F1",
        "source_color": "#000000",
        "flag": "🇬🇧"
    },
    {
        "title": "Why Audi and Ferrari can already upgrade their F1 engines despite ADUO delay",
        "link": "https://www.autosport.com/f1/news/why-audi-and-ferrari-can-already-upgrade-their-f1-engines-despite-aduo-delay/10833076/?utm_source=RSS&utm_medium=referral&utm_campaign=RSS-F1&utm_term=News&utm_content=uk",
        "image_url": "https://cdn-7.motorsport.com/images/amp/2wlE1q8Y/s6/charles-leclerc-ferrari-isack--2.jpg",
        "w": 1200,
        "h": 797,
        "focus_y": 0.5,
        "source_title1": "AUTOSPORT",
        "source_title2": "F1",
        "source_color": "#000000",
        "flag": "🇬🇧"
    },
    {
        "title": "FIA declares Heat Hazard for F1 Austrian Grand Prix",
        "link": "https://www.autosport.com/f1/news/fia-declares-heat-hazard-for-f1-austrian-grand-prix/10833039/?utm_source=RSS&utm_medium=referral&utm_campaign=RSS-F1&utm_term=News&utm_content=uk",
        "image_url": "https://cdn-6.motorsport.com/images/amp/6l9rE310/s6/lando-norris-mclaren-oscar-pia.jpg",
        "w": 1200,
        "h": 799,
        "focus_y": 0.5,
        "source_title1": "AUTOSPORT",
        "source_title2": "F1",
        "source_color": "#000000",
        "flag": "🇬🇧"
    }
]