{
  "created_at": "2026-07-03T00:08:38.598734+00:00",
  "created_by": "rss_gp1.py",
  "articles": [
    {
      "title": "Silverstone kao veliki test nove generacije bolida – hoće li utrkivanje patiti?",
      "link": "https://www.gp1.hr/2026/07/silverstone-kao-veliki-test-nove-generacije-bolida-hoce-li-utrkivanje-patiti/",
      "author": "Igor Šestak",
      "published_at": "2026-07-02T19:11:43+00:00",
      "image_url": "https://s.w.org/images/core/emoji/14.0.0/72x72/2b06.png",
      "w": 0,
      "h": 0,
      "focus_y": 0.5,
      "source_title1": "GP1",
      "source_title2": "F1",
      "source_color": "#FF0000",
      "flag": "🇭🇷"
    },
    {
      "title": "MXGP: Veliki transferi na pomolu? Paddock već bruji o 2027.",
      "link": "https://www.gp1.hr/2026/07/mxgp-veliki-transferi-na-pomolu-paddock-vec-bruji-o-2027/",
      "author": "GeaGP",
      "published_at": "2026-07-02T13:31:17+00:00",
      "image_url": "https://www.gp1.hr/wp-content/uploads/2026/07/RENAUX-MOTOCROSS-GP-9-ITA-2026.jpg",
      "w": 0,
      "h": 0,
      "focus_y": 0.5,
      "source_title1": "GP1",
      "source_title2": "F1",
      "source_color": "#FF0000",
      "flag": "🇭🇷"
    },
    {
      "title": "OSV Nagrada Grada Jastrebarskog: Jurnjava oko čunjeva u Gymkhana stilu",
      "link": "https://www.gp1.hr/2026/07/osv-nagrada-grada-jastrebarskog-jurnjava-oko-cunjeva-u-gymkhana-stilu/",
      "author": "GP1_hr",
      "published_at": "2026-07-01T13:38:00+00:00",
      "image_url": "https://www.gp1.hr/wp-content/uploads/2026/07/OSV-Jastrebarsko-2026-plakat.jpg",
      "w": 0,
      "h": 0,
      "focus_y": 0.5,
      "source_title1": "GP1",
      "source_title2": "F1",
      "source_color": "#FF0000",
      "flag": "🇭🇷"
    },
    {
      "title": "Brdska auto utrka 32. Nagrada Stubičkih toplica: Magdiću generalka, Prodanu kategorija",
      "link": "https://www.gp1.hr/2026/07/brdska-auto-utrka-32-nagrada-stubickih-toplica-magdicu-generalka-prodanu-kategorija/",
      "author": "GP1_hr",
      "published_at": "2026-07-01T11:48:00+00:00",
      "image_url": "https://www.gp1.hr/wp-content/uploads/2026/07/VILIAM-PRODAN-snimio-M.Krpan_.jpg",
      "w": 0,
      "h": 0,
      "focus_y": 0.5,
      "source_title1": "GP1",
      "source_title2": "F1",
      "source_color": "#FF0000",
      "flag": "🇭🇷"
    },
    {
      "title": "Prvenstvo Europe na brdskim stazama: Jurišiću 22. europska pobjeda",
      "link": "https://www.gp1.hr/2026/06/prvenstvo-europe-na-brdskim-stazama-jurisicu-22-europska-pobjeda/",
      "author": "GP1_hr",
      "published_at": "2026-06-30T06:55:00+00:00",
      "image_url": "",
      "w": 0,
      "h": 0,
      "focus_y": 0.5,
      "source_title1": "GP1",
      "source_title2": "F1",
      "source_color": "#FF0000",
      "flag": "🇭🇷"
    },
    {
      "title": "Wolff: Red Bull je bio brz radi Maxa",
      "link": "https://www.gp1.hr/2026/06/wolff-red-bull-je-bio-brz-radi-maxa/",
      "author": "Igor Vukajlovic",
      "published_at": "2026-06-29T18:37:55+00:00",
      "image_url": "",
      "w": 0,
      "h": 0,
      "focus_y": 0.5,
      "source_title1": "GP1",
      "source_title2": "F1",
      "source_color": "#FF0000",
      "flag": "🇭🇷"
    },
    {
      "title": "George Russell pobjednik VN Austrije!",
      "link": "https://www.gp1.hr/2026/06/george-russell-pobjednik-vn-austrije/",
      "author": "fermen",
      "published_at": "2026-06-28T14:30:08+00:00",
      "image_url": "https://s.w.org/images/core/emoji/14.0.0/72x72/1f3c6.png",
      "w": 0,
      "h": 0,
      "focus_y": 0.5,
      "source_title1": "GP1",
      "source_title2": "F1",
      "source_color": "#FF0000",
      "flag": "🇭🇷"
    },
    {
      "title": "Vasseur: Moramo vjerovati ljudima u kontroli utrke",
      "link": "https://www.gp1.hr/2026/06/vasseur-moramo-vjerovati-ljudima-u-kontroli-utrke/",
      "author": "Igor Šestak",
      "published_at": "2026-06-28T07:02:46+00:00",
      "image_url": "",
      "w": 0,
      "h": 0,
      "focus_y": 0.5,
      "source_title1": "GP1",
      "source_title2": "F1",
      "source_color": "#FF0000",
      "flag": "🇭🇷"
    },
    {
      "title": "Verstappen o nesreći u kvalifikacijama: Stvarno ne mogu objasniti",
      "link": "https://www.gp1.hr/2026/06/verstappen-o-nesreci-u-kvalifikacijama-stvarno-ne-mogu-objasniti/",
      "author": "Igor Šestak",
      "published_at": "2026-06-28T06:32:28+00:00",
      "image_url": "",
      "w": 0,
      "h": 0,
      "focus_y": 0.5,
      "source_title1": "GP1",
      "source_title2": "F1",
      "source_color": "#FF0000",
      "flag": "🇭🇷"
    },
    {
      "title": "Russell najbrži u kvalifikacijama u Austriji!",
      "link": "https://www.gp1.hr/2026/06/russell-najbrzi-u-kvalifikacijama-u-austriji/",
      "author": "Tomislav Radić",
      "published_at": "2026-06-27T15:13:25+00:00",
      "image_url": "https://www.gp1.hr/wp-content/uploads/2026/06/austrija-2026-kvale.jpg",
      "w": 0,
      "h": 0,
      "focus_y": 0.5,
      "source_title1": "GP1",
      "source_title2": "F1",
      "source_color": "#FF0000",
      "flag": "🇭🇷"
    }
  ]
}