[
    {
        "title": "2026 World Cup: List of squads, players announced so far",
        "link": "https://www.espn.com/soccer/story/_/id/48757621/2026-world-cup-squad-lists-players-announced-all-48-teams",
        "image_url": "https://a.espncdn.com/photo/2026/0320/r1630980_1296x729_16-9.jpg",
        "w": 1296,
        "h": 729,
        "focus_y": 0.35,
        "source_title1": "ESPN",
        "source_title2": "FOOTBALL",
        "source_color": "#ff0021",
        "flag": "🇺🇸"
    },
    {
        "title": "Transfer rumors, news: PSG made offer for Barça target Álvarez",
        "link": "https://www.espn.com/soccer/story/_/id/48936654/transfer-rumors-news-real-madrid-show-interest-arsenal-declan-rice",
        "image_url": "https://a.espncdn.com/photo/2026/0211/r1613892_1296x729_16-9.jpg",
        "w": 1296,
        "h": 729,
        "focus_y": 0.35,
        "source_title1": "ESPN",
        "source_title2": "FOOTBALL",
        "source_color": "#ff0021",
        "flag": "🇺🇸"
    },
    {
        "title": "Southampton Spygate messages reveal pressure put on junior staff by manager",
        "link": "https://www.espn.com/soccer/story/_/id/48940965/southampton-spygate-messages-reveal-pressure-put-junior-staff-manager",
        "image_url": "https://a.espncdn.com/photo/2026/0508/r1655249_1296x729_16-9.jpg",
        "w": 1296,
        "h": 729,
        "focus_y": 0.35,
        "source_title1": "ESPN",
        "source_title2": "FOOTBALL",
        "source_color": "#ff0021",
        "flag": "🇺🇸"
    },
    {
        "title": "Haaland sits, Isak scores as Norway beats Sweden in warmup",
        "link": "https://www.espn.com/soccer/story/_/id/48940831/haaland-sits-isak-scores-norway-beats-sweden",
        "image_url": "https://a.espncdn.com/photo/2026/0601/r1666759_1296x729_16-9.jpg",
        "w": 1296,
        "h": 729,
        "focus_y": 0.35,
        "source_title1": "ESPN",
        "source_title2": "FOOTBALL",
        "source_color": "#ff0021",
        "flag": "🇺🇸"
    },
    {
        "title": "USA at the 2026 World Cup: Schedule, results, how to watch, news, analysis, injuries, more",
        "link": "https://www.espn.com/soccer/story/_/id/48940468/usa-world-cup-2026-schedule-fixtures-results-scores-group-d-how-watch-news-analysis-injuries",
        "image_url": "https://a.espncdn.com/photo/2026/0601/r1666774_1296x729_16-9.jpg",
        "w": 1296,
        "h": 729,
        "focus_y": 0.35,
        "source_title1": "ESPN",
        "source_title2": "FOOTBALL",
        "source_color": "#ff0021",
        "flag": "🇺🇸"
    },
    {
        "title": "USMNT snub in 2022 helped Ricardo Pepi make 2026 World Cup squad",
        "link": "https://www.espn.com/soccer/story/_/id/48940196/usmnt-snub-2022-helped-ricardo-pepi-2026-world-cup",
        "image_url": "https://a.espncdn.com/photo/2026/0601/r1666784_1296x729_16-9.jpg",
        "w": 1296,
        "h": 729,
        "focus_y": 0.35,
        "source_title1": "ESPN",
        "source_title2": "FOOTBALL",
        "source_color": "#ff0021",
        "flag": "🇺🇸"
    },
    {
        "title": "Queiroz defends Partey's inclusion in Ghana squad vs. Wales",
        "link": "https://www.espn.com/soccer/story/_/id/48939953/queiroz-defends-partey-inclusion-ghana-wales",
        "image_url": "https://a.espncdn.com/photo/2025/0916/r1546736_1296x729_16-9.jpg",
        "w": 1296,
        "h": 729,
        "focus_y": 0.35,
        "source_title1": "ESPN",
        "source_title2": "FOOTBALL",
        "source_color": "#ff0021",
        "flag": "🇺🇸"
    },
    {
        "title": "Crysencio Summerville 'surprised' at Netherlands World Cup call-up",
        "link": "https://www.espn.com/soccer/story/_/id/48940084/crysencio-summerville-surprised-netherlands-world-cup-call-up",
        "image_url": "https://a.espncdn.com/photo/2025/1023/r1564555_1296x729_16-9.jpg",
        "w": 1296,
        "h": 729,
        "focus_y": 0.35,
        "source_title1": "ESPN",
        "source_title2": "FOOTBALL",
        "source_color": "#ff0021",
        "flag": "🇺🇸"
    },
    {
        "title": "Chelsea sign Katie McCabe from Arsenal on free transfer",
        "link": "https://www.espn.com/soccer/story/_/id/48939623/chelsea-sign-katie-mccabe-arsenal-free-transfer",
        "image_url": "https://a.espncdn.com/photo/2025/1116/r1576265_1296x729_16-9.jpg",
        "w": 1296,
        "h": 729,
        "focus_y": 0.35,
        "source_title1": "ESPN",
        "source_title2": "FOOTBALL",
        "source_color": "#ff0021",
        "flag": "🇺🇸"
    },
    {
        "title": "Iran star Sardar Azmoun shock omission from World Cup squad",
        "link": "https://www.espn.com/soccer/story/_/id/48939448/iran-star-sardar-azmoun-shock-omission-world-cup-squad",
        "image_url": "https://a.espncdn.com/photo/2026/0601/r1666737_1296x729_16-9.jpg",
        "w": 1296,
        "h": 729,
        "focus_y": 0.35,
        "source_title1": "ESPN",
        "source_title2": "FOOTBALL",
        "source_color": "#ff0021",
        "flag": "🇺🇸"
    },
    {
        "title": "Craig Bellamy reaffirms commitment to Wales amid reported interest",
        "link": "https://www.espn.com/soccer/story/_/id/48939519/craig-bellamy-reaffirms-commitment-wales-amid-reported-interest",
        "image_url": "https://a.espncdn.com/photo/2026/0325/r1633774_2_1296x729_16-9.jpg",
        "w": 1296,
        "h": 729,
        "focus_y": 0.35,
        "source_title1": "ESPN",
        "source_title2": "FOOTBALL",
        "source_color": "#ff0021",
        "flag": "🇺🇸"
    },
    {
        "title": "Portugal will draw on memory of Diogo Jota for strength at World Cup - Neves",
        "link": "https://www.espn.com/soccer/story/_/id/48939481/portugal-draw-memory-diogo-jota-strength-world-cup-neves",
        "image_url": "https://a.espncdn.com/photo/2025/0919/r1547841_1296x729_16-9.jpg",
        "w": 1296,
        "h": 729,
        "focus_y": 0.35,
        "source_title1": "ESPN",
        "source_title2": "FOOTBALL",
        "source_color": "#ff0021",
        "flag": "🇺🇸"
    },
    {
        "title": "Andrés Iniesta gets first managerial job at second-tier UAE side",
        "link": "https://www.espn.com/soccer/story/_/id/48938980/andres-iniesta-first-managerial-job-second-tier-uae-side-gulf-united",
        "image_url": "https://a.espncdn.com/photo/2026/0601/r1666673_1296x729_16-9.jpg",
        "w": 1296,
        "h": 729,
        "focus_y": 0.35,
        "source_title1": "ESPN",
        "source_title2": "FOOTBALL",
        "source_color": "#ff0021",
        "flag": "🇺🇸"
    },
    {
        "title": "NWSL Power Rankings: Utah keeps spot at the top as Portland tumbles",
        "link": "https://www.espn.com/soccer/story/_/id/48938302/nwsl-power-rankings-utah-royals-keep-spot-top-portland-thorns-tumble",
        "image_url": "https://a.espncdn.com/photo/2026/0601/r1666651_1296x729_16-9.jpg",
        "w": 1297,
        "h": 729,
        "focus_y": 0.35,
        "source_title1": "ESPN",
        "source_title2": "FOOTBALL",
        "source_color": "#ff0021",
        "flag": "🇺🇸"
    },
    {
        "title": "Arsenal parade: Six stabbings, 75 people rescued from heights",
        "link": "https://www.espn.com/soccer/story/_/id/48937142/arsenal-parade-sixteen-arrests-75-people-rescued-heights",
        "image_url": "https://a.espncdn.com/photo/2026/0601/r1666563_1296x729_16-9.jpg",
        "w": 1296,
        "h": 729,
        "focus_y": 0.35,
        "source_title1": "ESPN",
        "source_title2": "FOOTBALL",
        "source_color": "#ff0021",
        "flag": "🇺🇸"
    }
]