[
    {
        "title": "‘Servis nakon utakmice‘ koristili i poznati nogometaši? Objavljeno koliko su plaćali večer s djevojkama Radilo se o vrlo mladim djevojkama, često tek punoljetnim, u mnogim slučajevima strankinjama iz Južne Amerike ili Istočne Europe",
        "link": "https://sportske.jutarnji.hr/sportske/nogomet/nogomet-mix/milanski-servis-nakon-utakmice-eskort-plin-smijavac-uhicenja-skandal-serie-a-15701020",
        "image_url": "https://media.jutarnji.hr/images/slike/2026/04/21/k_28692419_640.jpg",
        "w": 640,
        "h": 640,
        "focus_y": 0.35,
        "source_title1": "SPORTSKE",
        "source_title2": "NOVOSTI",
        "source_color": "#007aff",
        "flag": "🇭🇷"
    },
    {
        "title": "Skandal za skandalom trese saveze, hrvatski sportaši mogli bi se naći u novom problemu",
        "link": "https://sportske.jutarnji.hr/sportske/sport-mix/skandali-u-savezima-buducnost-financiranja-hrvatskog-sporta-15700976",
        "image_url": "https://media.jutarnji.hr/images/slike/2026/04/21/k_38637249_640.jpg",
        "w": 640,
        "h": 640,
        "focus_y": 0.35,
        "source_title1": "SPORTSKE",
        "source_title2": "NOVOSTI",
        "source_color": "#007aff",
        "flag": "🇭🇷"
    },
    {
        "title": "Layec presudio: Dinamu opravdano poništen gol, sva tri penala čista, ali izgubilo se previše vremena",
        "link": "https://sportske.jutarnji.hr/sportske/nogomet/hnl/layec-presudio-dinamu-opravdano-ponisten-gol-sva-tri-penala-cista-ali-izgubilo-se-previse-vremena-15701071",
        "image_url": "https://media.jutarnji.hr/images/slike/2026/04/21/k_38768236_640.jpg",
        "w": 640,
        "h": 640,
        "focus_y": 0.35,
        "source_title1": "SPORTSKE",
        "source_title2": "NOVOSTI",
        "source_color": "#007aff",
        "flag": "🇭🇷"
    },
    {
        "title": "UŽIVO Lokomotiva - Slaven: Počeo je okršaj na Maksimiru, Lokosi u borbi za Europu s...",
        "link": "https://sportske.jutarnji.hr/sportske/nogomet/hnl/lokomotiva-slaven-belupo-maksimir-bodovi-za-europski-iskorak-uzivo-15701059",
        "image_url": "https://media.jutarnji.hr/images/slike/2026/04/21/k_38530075_640.jpg",
        "w": 640,
        "h": 640,
        "focus_y": 0.35,
        "source_title1": "SPORTSKE",
        "source_title2": "NOVOSTI",
        "source_color": "#007aff",
        "flag": "🇭🇷"
    },
    {
        "title": "‘Da, SHNL je u padu! Ovo je potvrdio i Dalić, a znate li što mi je rekao Selahi kad je otišao?‘",
        "link": "https://sportske.jutarnji.hr/sportske/nogomet/hnl/graf-razgolitio-shnl-sopic-otkriva-razliku-poljaci-lete-mi-hodamo-15700912",
        "image_url": "https://media.jutarnji.hr/images/slike/2026/04/19/k_38287863_640.jpg",
        "w": 640,
        "h": 640,
        "focus_y": 0.35,
        "source_title1": "SPORTSKE",
        "source_title2": "NOVOSTI",
        "source_color": "#007aff",
        "flag": "🇭🇷"
    },
    {
        "title": "Warriorse ne zanima patetika ‘posljednjeg plesa‘, Kerr će ostati samo ako je još ‘gladan‘",
        "link": "https://sportske.jutarnji.hr/sportske/kosarka/nba/warriorse-ne-zanima-patetika-posljednjeg-plesa-kerr-ce-ostati-samo-ako-je-jos-gladan-15701080",
        "image_url": "https://media.jutarnji.hr/images/slike/2026/04/21/k_38766570_640.jpg",
        "w": 640,
        "h": 640,
        "focus_y": 0.35,
        "source_title1": "SPORTSKE",
        "source_title2": "NOVOSTI",
        "source_color": "#007aff",
        "flag": "🇭🇷"
    },
    {
        "title": "Skandalozni detalji: Šteta u šahovskom savezu čak 190.000 eura? Podnesena prijava protiv velemajstora",
        "link": "https://sportske.jutarnji.hr/sportske/sport-mix/chess/hss-prijavio-alojzija-jankovica-zbog-pronevjere-i-prijevare-steta-190000-eura-15700956",
        "image_url": "https://media.jutarnji.hr/images/slike/2026/04/21/k_38033706_640.jpg",
        "w": 640,
        "h": 640,
        "focus_y": 0.35,
        "source_title1": "SPORTSKE",
        "source_title2": "NOVOSTI",
        "source_color": "#007aff",
        "flag": "🇭🇷"
    },
    {
        "title": "Kovačević najavio prekid crne serije u Puli i otkrio tko ostaje u Zagrebu: ‘Nisu spremni‘",
        "link": "https://sportske.jutarnji.hr/sportske/nogomet/hnl/klubovi/dinamo/dinamo-istria-kovacevic-najava-drosina-prekid-crnog-niza-ozljede-15701017",
        "image_url": "https://media.jutarnji.hr/images/slike/2026/04/21/k_38693655_640.jpg",
        "w": 640,
        "h": 640,
        "focus_y": 0.35,
        "source_title1": "SPORTSKE",
        "source_title2": "NOVOSTI",
        "source_color": "#007aff",
        "flag": "🇭🇷"
    },
    {
        "title": "Tradicija najveće utrke na svijetu proteže se kroz tri stoljeća, među pobjednicima i Hrvat",
        "link": "https://sportske.jutarnji.hr/sportske/sport-mix/atletika/tradicija-najvece-utrke-na-svijetu-proteze-se-kroz-tri-stoljeca-medu-pobjednicima-i-hrvat-15701052",
        "image_url": "https://media.jutarnji.hr/images/slike/2026/04/20/k_38775900_640.jpg",
        "w": 640,
        "h": 640,
        "focus_y": 0.35,
        "source_title1": "SPORTSKE",
        "source_title2": "NOVOSTI",
        "source_color": "#007aff",
        "flag": "🇭🇷"
    },
    {
        "title": "‘Krajač nije smio biti izabran, ali nije bilo tako! Prosudite sami je li važno što nisam član stranke‘",
        "link": "https://sportske.jutarnji.hr/sportske/sport-mix/chess/alojzije-jankovic-odbacuje-prijavu-hss-a-i-najavljuje-sud-15701036",
        "image_url": "https://media.jutarnji.hr/images/slike/2026/04/21/k_29295191_640.jpg",
        "w": 640,
        "h": 640,
        "focus_y": 0.35,
        "source_title1": "SPORTSKE",
        "source_title2": "NOVOSTI",
        "source_color": "#007aff",
        "flag": "🇭🇷"
    },
    {
        "title": "‘Kupaći curama ponekad zna skliznuti, a komentari budu...",
        "link": "https://sportske.jutarnji.hr/sportske/sport-mix/vaterpolo/mia-simunic-predsude-kupaci-istina-zenski-vaterpolo-sportcast-15700488",
        "image_url": "https://media.jutarnji.hr/images/slike/2026/04/20/k_38756658_640.jpg",
        "w": 640,
        "h": 640,
        "focus_y": 0.35,
        "source_title1": "SPORTSKE",
        "source_title2": "NOVOSTI",
        "source_color": "#007aff",
        "flag": "🇭🇷"
    },
    {
        "title": "Legenda Vatrenih otkrila gdje je Modrić počeo tražiti stan: ‘Ne ulazim u obiteljske stvari...‘",
        "link": "https://sportske.jutarnji.hr/sportske/nogomet/simic-modric-trazi-stan-u-milanu-ugovor-istjece-30-lipnja-15700614",
        "image_url": "https://media.jutarnji.hr/images/slike/2026/04/20/k_37444702_640.jpg",
        "w": 640,
        "h": 640,
        "focus_y": 0.35,
        "source_title1": "SPORTSKE",
        "source_title2": "NOVOSTI",
        "source_color": "#007aff",
        "flag": "🇭🇷"
    },
    {
        "title": "Strašne vijesti iz Italije: Sin legende slomio vrat, odvezli ga u bolnicu",
        "link": "https://sportske.jutarnji.hr/sportske/nogomet/nogomet-mix/jonathan-klinsmann-slomio-vratni-kraljezak-zavrsio-sezonu-serie-b-15700814",
        "image_url": "https://media.jutarnji.hr/images/slike/2026/04/20/k_38775108_640.jpg",
        "w": 640,
        "h": 640,
        "focus_y": 0.35,
        "source_title1": "SPORTSKE",
        "source_title2": "NOVOSTI",
        "source_color": "#007aff",
        "flag": "🇭🇷"
    },
    {
        "title": "Provaljen VIP lanac prostitucije: Zbog ‘usluge nakon utakmice‘ dolazili čak i oni koji nisu igrali!?",
        "link": "https://sportske.jutarnji.hr/sportske/sport-mix/automoto/formula1/milano-razbijena-mreza-luksuzne-prostitucije-za-sportase-i-vip-klijente-15700908",
        "image_url": "https://media.jutarnji.hr/images/slike/2026/04/21/k_24387137_640.jpg",
        "w": 640,
        "h": 640,
        "focus_y": 0.35,
        "source_title1": "SPORTSKE",
        "source_title2": "NOVOSTI",
        "source_color": "#007aff",
        "flag": "🇭🇷"
    },
    {
        "title": "Zbog velike pogreške nemaju šanse ući u HNL! Doznajemo: Zahtjev im neće proći",
        "link": "https://sportske.jutarnji.hr/sportske/nogomet/hnl/druga-hnl/rudes-blizu-shnl-a-sesvete-bez-licence-hns-odluke-15700742",
        "image_url": "https://media.jutarnji.hr/images/slike/2026/04/20/k_37736781_640.jpg",
        "w": 640,
        "h": 640,
        "focus_y": 0.35,
        "source_title1": "SPORTSKE",
        "source_title2": "NOVOSTI",
        "source_color": "#007aff",
        "flag": "🇭🇷"
    },
    {
        "title": "U 78. godini napustio nas je istinski vizionar Dragan Milanović Njegov potpis nalazi se u uspjesima brojnih klubova i reprezentacija, od odbojke i vaterpola do rukometa i košarke",
        "link": "https://sportske.jutarnji.hr/sportske/sport-mix/ostali-sportovi/preminuo-dragan-milanovic-pionir-kondicijske-pripreme-hrvatska-15701026",
        "image_url": "https://media.jutarnji.hr/images/slike/2026/04/21/k_38776856_640.jpg",
        "w": 640,
        "h": 640,
        "focus_y": 0.35,
        "source_title1": "SPORTSKE",
        "source_title2": "NOVOSTI",
        "source_color": "#007aff",
        "flag": "🇭🇷"
    },
    {
        "title": "Suigrač Vatrenog izboden, klub objavio izvanredno priopćenje: ‘Molimo za razumijevanje‘",
        "link": "https://sportske.jutarnji.hr/sportske/nogomet/alamara-djabi-izboden-u-herningu-probuden-iz-kome-15700951",
        "image_url": "https://media.jutarnji.hr/images/slike/2026/04/21/k_37732762_640.jpg",
        "w": 640,
        "h": 640,
        "focus_y": 0.35,
        "source_title1": "SPORTSKE",
        "source_title2": "NOVOSTI",
        "source_color": "#007aff",
        "flag": "🇭🇷"
    },
    {
        "title": "Hajduku se danas vraćaju dva važna aduta? Ovo je vjerojatni sastav Bijelih za okršaj na Poljudu",
        "link": "https://sportske.jutarnji.hr/sportske/nogomet/hnl/klubovi/hajduk/hajduk-osijek-garcia-rotacije-sego-sigur-bez-livaje-krovinovica-tri-boda-15700865",
        "image_url": "https://media.jutarnji.hr/images/slike/2026/04/20/k_38741154_640.jpg",
        "w": 640,
        "h": 640,
        "focus_y": 0.35,
        "source_title1": "SPORTSKE",
        "source_title2": "NOVOSTI",
        "source_color": "#007aff",
        "flag": "🇭🇷"
    },
    {
        "title": "Sanchez u jednu od najvažnijih utakmica ulazi bez više od pola momčadi, ali kreće s dva napadača?",
        "link": "https://sportske.jutarnji.hr/sportske/nogomet/hnl/klubovi/rijeka/rijeka-oslabljena-trazi-prekretnicu-i-tri-boda-u-varazdinu-15700930",
        "image_url": "https://media.jutarnji.hr/images/slike/2026/04/20/k_38694141_640.jpg",
        "w": 640,
        "h": 640,
        "focus_y": 0.35,
        "source_title1": "SPORTSKE",
        "source_title2": "NOVOSTI",
        "source_color": "#007aff",
        "flag": "🇭🇷"
    },
    {
        "title": "Kraj jedne ere: Guardiolin miljenik odlazi iz Manchester Cityja nakon 10 godina i 17 trofeja!",
        "link": "https://sportske.jutarnji.hr/sportske/nogomet/john-stones-napusta-manchester-city-slobodan-igrac-deset-godina-15700864",
        "image_url": "https://media.jutarnji.hr/images/slike/2026/04/21/k_29931633_640.jpg",
        "w": 640,
        "h": 640,
        "focus_y": 0.35,
        "source_title1": "SPORTSKE",
        "source_title2": "NOVOSTI",
        "source_color": "#007aff",
        "flag": "🇭🇷"
    }
]